
[
    {
        "id": "D4C7F659-AEEB-4E19-8413-59A400DA7C9E",
        "title": "Budget 1",
        "note": "Test",
        "estimatedAmount": 100.0,
        "date": "2024-09-03T08:30:00Z",
        "createdDate": "2024-09-03T08:30:00Z",
        "updatedDate": "2024-09-03T08:30:00Z",
        "isTimeEnabled": false,
        "totalIncomes": 0.0,
        "totalExpenses": 0.0,
    },
    {
        "id": "2CF4D477-4E12-4E83-BDEC-944943697786",
        "title": "Budget 2",
        "note": "Test",
        "estimatedAmount": 123.0,
        "date": "2024-09-03T08:30:00Z",
        "createdDate": "2024-09-03T08:30:00Z",
        "updatedDate": "2024-09-03T08:30:00Z",
        "isTimeEnabled": false,
        "totalIncomes": 0.0,
        "totalExpenses": 0.0,
    },
    {
        "id": "C92DECA3-C62F-4418-9D85-14D8C0375B37",
        "title": "Budget 3",
        "note": "Test",
        "estimatedAmount": 3.0,
        "date": "2024-09-03T08:30:00Z",
        "createdDate": "2024-09-03T08:30:00Z",
        "updatedDate": "2024-09-03T08:30:00Z",
        "isTimeEnabled": false,
        "totalIncomes": 0.0,
        "totalExpenses": 0.0,
    },
]
